{"tabela":[{"campo":"G&E MANUTENÇÃO E SERVIÇOS LTDA","total":2376971.65},
{"campo":"CONSTRUTORA NORBERTO ODEBRECHT S A","total":1274692.37},
{"campo":"MILLS SI SERVICOS INDUSTRIAIS S/A","total":1227968.98},
{"campo":"MKS CALDEIRARIA INDUSTRIA E COMERCIO LTDA","total":1046623.05},
{"campo":"LIS TRANSPORTES E TURISMO LTDA ME","total":703416.11},
{"campo":"ASPIL ASPIRACAO INDUSTRIAL E SERVICOS LTDA","total":679063.59},
{"campo":"PINTURAS YPIRANGA LTDA","total":630508.92},
{"campo":"EXPRESSO NEPOMUCENO S/A","total":624423.03},
{"campo":"ELINQ - COOPERATIVA DE TRABALHO DE MONTAGEM E MANUTENCAO INDUSTRIAL","total":488716.51},
{"campo":"PHL PROFISSIONAIS DE HIGIENE E LIMPEZA LTDA-ME","total":461354.10}]}

